{"title":"Primer trabajo: Optimización heurística","markdown":{"yaml":{"title":"Primer trabajo: Optimización heurística","author":[{"name":"Catalina Restrepo Salgado"},{"name":"Julián Castaño Pineda"},{"name":"Tomás Rodríguez Taborda"},{"name":"Luis Andrés Altamar Romero"}],"date":"2024-11-15","categories":["optimización"],"image":"image.jpg"},"headingText":"Primera parte: Optimización Numérica","containsRefs":false,"markdown":"\n\n\n## Considere las siguientes funciones de prueba:\n- **Función de Rosenbrock**\n- **Función de Rastrigin**\n- **Función de Schwefel**\n- **Función de Griewank**\n- **Función Goldstein-Price**\n- **Función de las seis jorobas de camello**\n\n### Tareas:\n1. **Escoja dos funciones de prueba.**\n2. **Optimización con método de descenso por gradiente:**\n   - Optimice las funciones seleccionadas en **dos y tres dimensiones** usando un **método de descenso por gradiente** con condición inicial aleatoria.\n3. **Optimización con métodos heurísticos:**\n   - Optimice las funciones seleccionadas en **dos y tres dimensiones** usando:\n     - Algoritmos evolutivos.\n     - Optimización de partículas.\n     - Evolución diferencial.\n4. **Representación visual:**\n   - Cree un **GIF animado** o un **video** que muestre el proceso de optimización usando:\n     - **Descenso por gradiente**.\n     - **Métodos heurísticos**.\n\n### Discusión:\nReflexione sobre los siguientes puntos:\n- ¿Qué aportaron los métodos de **descenso por gradiente** y qué aportaron los **métodos heurísticos**?\n  - Para responder a esta pregunta, considere:\n    - El **valor final** de la función objetivo.\n    - El **número de evaluaciones** de la función objetivo.\n  - Es posible que se requiera realizar **varias corridas** de los algoritmos para obtener conclusiones significativas.\n\n\n# Parte 2: Optimización Combinatoria\n\n## Problema del Viajero:\nUn vendedor debe realizar un recorrido por **todas las capitales** de los **32 estados** de los **Estados Unidos Mexicanos**.\n\n### Tareas:\n1. **Optimización con métodos metaheurísticos:**\n   - Utilice **colonias de hormigas** para encontrar el orden óptimo del recorrido.\n   - Utilice **algoritmos genéticos** para encontrar el orden óptimo del recorrido.\n2. **Costo del recorrido:**\n   - El costo de desplazamiento entre ciudades se calcula como la suma de:\n     - El valor de la **hora del vendedor** (este es un parámetro que debe estudiarse).\n     - El **costo de los peajes**.\n     - El **costo del combustible**.\n   - Cada equipo debe definir el **vehículo** que utilizará el vendedor para realizar el recorrido y, con base en esta elección, **calcular el costo del combustible**.\n\n### Representación Visual:\n- Cree un **GIF animado** o un **video** que muestre cómo se comporta la **mejor solución** encontrada, usando un **gráfico del recorrido** en el mapa de México.\n\n---\n\n### Discusión:\nReflexione sobre:\n- Los resultados obtenidos con las **colonias de hormigas** y los **algoritmos genéticos**.\n- Comparación de costos y tiempo de ejecución.","srcMarkdownNoYaml":"\n\n# Primera parte: Optimización Numérica\n\n## Considere las siguientes funciones de prueba:\n- **Función de Rosenbrock**\n- **Función de Rastrigin**\n- **Función de Schwefel**\n- **Función de Griewank**\n- **Función Goldstein-Price**\n- **Función de las seis jorobas de camello**\n\n### Tareas:\n1. **Escoja dos funciones de prueba.**\n2. **Optimización con método de descenso por gradiente:**\n   - Optimice las funciones seleccionadas en **dos y tres dimensiones** usando un **método de descenso por gradiente** con condición inicial aleatoria.\n3. **Optimización con métodos heurísticos:**\n   - Optimice las funciones seleccionadas en **dos y tres dimensiones** usando:\n     - Algoritmos evolutivos.\n     - Optimización de partículas.\n     - Evolución diferencial.\n4. **Representación visual:**\n   - Cree un **GIF animado** o un **video** que muestre el proceso de optimización usando:\n     - **Descenso por gradiente**.\n     - **Métodos heurísticos**.\n\n### Discusión:\nReflexione sobre los siguientes puntos:\n- ¿Qué aportaron los métodos de **descenso por gradiente** y qué aportaron los **métodos heurísticos**?\n  - Para responder a esta pregunta, considere:\n    - El **valor final** de la función objetivo.\n    - El **número de evaluaciones** de la función objetivo.\n  - Es posible que se requiera realizar **varias corridas** de los algoritmos para obtener conclusiones significativas.\n\n\n# Parte 2: Optimización Combinatoria\n\n## Problema del Viajero:\nUn vendedor debe realizar un recorrido por **todas las capitales** de los **32 estados** de los **Estados Unidos Mexicanos**.\n\n### Tareas:\n1. **Optimización con métodos metaheurísticos:**\n   - Utilice **colonias de hormigas** para encontrar el orden óptimo del recorrido.\n   - Utilice **algoritmos genéticos** para encontrar el orden óptimo del recorrido.\n2. **Costo del recorrido:**\n   - El costo de desplazamiento entre ciudades se calcula como la suma de:\n     - El valor de la **hora del vendedor** (este es un parámetro que debe estudiarse).\n     - El **costo de los peajes**.\n     - El **costo del combustible**.\n   - Cada equipo debe definir el **vehículo** que utilizará el vendedor para realizar el recorrido y, con base en esta elección, **calcular el costo del combustible**.\n\n### Representación Visual:\n- Cree un **GIF animado** o un **video** que muestre cómo se comporta la **mejor solución** encontrada, usando un **gráfico del recorrido** en el mapa de México.\n\n---\n\n### Discusión:\nReflexione sobre:\n- Los resultados obtenidos con las **colonias de hormigas** y los **algoritmos genéticos**.\n- Comparación de costos y tiempo de ejecución."},"formats":{"html":{"identifier":{"display-name":"HTML","target-format":"html","base-format":"html"},"execute":{"fig-width":7,"fig-height":5,"fig-format":"retina","fig-dpi":96,"df-print":"default","error":false,"eval":true,"cache":null,"freeze":true,"echo":true,"output":true,"warning":true,"include":true,"keep-md":false,"keep-ipynb":false,"ipynb":null,"enabled":null,"daemon":null,"daemon-restart":false,"debug":false,"ipynb-filters":[],"ipynb-shell-interactivity":null,"plotly-connected":true,"engine":"markdown"},"render":{"keep-tex":false,"keep-typ":false,"keep-source":false,"keep-hidden":false,"prefer-html":false,"output-divs":true,"output-ext":"html","fig-align":"default","fig-pos":null,"fig-env":null,"code-fold":"none","code-overflow":"scroll","code-link":false,"code-line-numbers":false,"code-tools":false,"tbl-colwidths":"auto","merge-includes":true,"inline-includes":false,"preserve-yaml":false,"latex-auto-mk":true,"latex-auto-install":true,"latex-clean":true,"latex-min-runs":1,"latex-max-runs":10,"latex-makeindex":"makeindex","latex-makeindex-opts":[],"latex-tlmgr-opts":[],"latex-input-paths":[],"latex-output-dir":null,"link-external-icon":false,"link-external-newwindow":false,"self-contained-math":false,"format-resources":[],"notebook-links":true},"pandoc":{"standalone":true,"wrap":"none","default-image-extension":"png","to":"html","css":["../../styles.css"],"output-file":"index.html"},"language":{"toc-title-document":"Table of contents","toc-title-website":"On this page","related-formats-title":"Other Formats","related-notebooks-title":"Notebooks","source-notebooks-prefix":"Source","other-links-title":"Other Links","code-links-title":"Code Links","launch-dev-container-title":"Launch Dev Container","launch-binder-title":"Launch Binder","article-notebook-label":"Article Notebook","notebook-preview-download":"Download Notebook","notebook-preview-download-src":"Download Source","notebook-preview-back":"Back to Article","manuscript-meca-bundle":"MECA Bundle","section-title-abstract":"Abstract","section-title-appendices":"Appendices","section-title-footnotes":"Footnotes","section-title-references":"References","section-title-reuse":"Reuse","section-title-copyright":"Copyright","section-title-citation":"Citation","appendix-attribution-cite-as":"For attribution, please cite this work as:","appendix-attribution-bibtex":"BibTeX citation:","appendix-view-license":"View License","title-block-author-single":"Author","title-block-author-plural":"Authors","title-block-affiliation-single":"Affiliation","title-block-affiliation-plural":"Affiliations","title-block-published":"Published","title-block-modified":"Modified","title-block-keywords":"Keywords","callout-tip-title":"Tip","callout-note-title":"Note","callout-warning-title":"Warning","callout-important-title":"Important","callout-caution-title":"Caution","code-summary":"Code","code-tools-menu-caption":"Code","code-tools-show-all-code":"Show All Code","code-tools-hide-all-code":"Hide All Code","code-tools-view-source":"View Source","code-tools-source-code":"Source Code","tools-share":"Share","tools-download":"Download","code-line":"Line","code-lines":"Lines","copy-button-tooltip":"Copy to Clipboard","copy-button-tooltip-success":"Copied!","repo-action-links-edit":"Edit this page","repo-action-links-source":"View source","repo-action-links-issue":"Report an issue","back-to-top":"Back to top","search-no-results-text":"No results","search-matching-documents-text":"matching documents","search-copy-link-title":"Copy link to search","search-hide-matches-text":"Hide additional matches","search-more-match-text":"more match in this document","search-more-matches-text":"more matches in this document","search-clear-button-title":"Clear","search-text-placeholder":"","search-detached-cancel-button-title":"Cancel","search-submit-button-title":"Submit","search-label":"Search","toggle-section":"Toggle section","toggle-sidebar":"Toggle sidebar navigation","toggle-dark-mode":"Toggle dark mode","toggle-reader-mode":"Toggle reader mode","toggle-navigation":"Toggle navigation","crossref-fig-title":"Figure","crossref-tbl-title":"Table","crossref-lst-title":"Listing","crossref-thm-title":"Theorem","crossref-lem-title":"Lemma","crossref-cor-title":"Corollary","crossref-prp-title":"Proposition","crossref-cnj-title":"Conjecture","crossref-def-title":"Definition","crossref-exm-title":"Example","crossref-exr-title":"Exercise","crossref-ch-prefix":"Chapter","crossref-apx-prefix":"Appendix","crossref-sec-prefix":"Section","crossref-eq-prefix":"Equation","crossref-lof-title":"List of Figures","crossref-lot-title":"List of Tables","crossref-lol-title":"List of Listings","environment-proof-title":"Proof","environment-remark-title":"Remark","environment-solution-title":"Solution","listing-page-order-by":"Order By","listing-page-order-by-default":"Default","listing-page-order-by-date-asc":"Oldest","listing-page-order-by-date-desc":"Newest","listing-page-order-by-number-desc":"High to Low","listing-page-order-by-number-asc":"Low to High","listing-page-field-date":"Date","listing-page-field-title":"Title","listing-page-field-description":"Description","listing-page-field-author":"Author","listing-page-field-filename":"File Name","listing-page-field-filemodified":"Modified","listing-page-field-subtitle":"Subtitle","listing-page-field-readingtime":"Reading Time","listing-page-field-wordcount":"Word Count","listing-page-field-categories":"Categories","listing-page-minutes-compact":"{0} min","listing-page-category-all":"All","listing-page-no-matches":"No matching items","listing-page-words":"{0} words","listing-page-filter":"Filter","draft":"Draft"},"metadata":{"lang":"en","fig-responsive":true,"quarto-version":"1.6.36","theme":"cosmo","title-block-banner":true,"title":"Primer trabajo: Optimización heurística","author":[{"name":"Catalina Restrepo Salgado"},{"name":"Julián Castaño Pineda"},{"name":"Tomás Rodríguez Taborda"},{"name":"Luis Andrés Altamar Romero"}],"date":"2024-11-15","categories":["optimización"],"image":"image.jpg"},"extensions":{"book":{"multiFile":true}}}},"projectFormats":["html"]}